bolt11/__init__.py
bolt11/compat.py
bolt11/core.py
bolt11/py.typed
bolt11/types.py
bolt11/utils.py
bolt11_voltage-0.0.1.4.dist-info/LICENSE
bolt11_voltage-0.0.1.4.dist-info/WHEEL
bolt11_voltage-0.0.1.4.dist-info/METADATA
bolt11_voltage-0.0.1.4.dist-info/RECORD
