Metadata-Version: 2.1
Name: bolt11-voltage
Version: 0.0.1.4
Summary: 
License: MIT
Author: eillarra
Author-email: eneko@illarra.com
Requires-Python: >=3.6.2,<4.0
Classifier: License :: OSI Approved :: MIT License
Classifier: Programming Language :: Python :: 3
Classifier: Programming Language :: Python :: 3.7
Classifier: Programming Language :: Python :: 3.8
Classifier: Programming Language :: Python :: 3.9
Classifier: Programming Language :: Python :: 3.10
Requires-Dist: base58 (>=2.1.1,<3.0.0)
Requires-Dist: bech32 (>=1.2.0,<2.0.0)
Requires-Dist: bitstring (>=3.1.9,<4.0.0)
Requires-Dist: ecdsa (>=0.17.0,<0.18.0)
Requires-Dist: typing-extensions (>=4.1.1,<5.0.0)
